xiaogui_ble/__init__.py
xiaogui_ble/parser.py
xiaogui_ble/py.typed
xiaogui_ble-0.1.1.dist-info/LICENSE
xiaogui_ble-0.1.1.dist-info/METADATA
xiaogui_ble-0.1.1.dist-info/WHEEL
xiaogui_ble-0.1.1.dist-info/RECORD
