Metadata-Version: 2.1
Name: xiaogui-ble
Version: 0.1.1
Summary: Bluetooth parser for xiaogui scales
Home-page: https://github.com/bluetooth-devices/xiaogui-ble
License: MIT
Author: J. Nick Koston
Author-email: bluetooth@koston.org
Requires-Python: >=3.11,<4.0
Classifier: Development Status :: 2 - Pre-Alpha
Classifier: Intended Audience :: Developers
Classifier: License :: OSI Approved :: MIT License
Classifier: Natural Language :: English
Classifier: Operating System :: OS Independent
Classifier: Programming Language :: Python :: 3
Classifier: Programming Language :: Python :: 3.11
Classifier: Programming Language :: Python :: 3.12
Classifier: Topic :: Software Development :: Libraries
Requires-Dist: bluetooth-data-tools (>=1.19.0)
Requires-Dist: bluetooth-sensor-state-data (>=1.6.2)
Project-URL: Bug Tracker, https://github.com/bluetooth-devices/xiaogui-ble/issues
Project-URL: Changelog, https://github.com/bluetooth-devices/xiaogui-ble/blob/main/CHANGELOG.md
Project-URL: Repository, https://github.com/bluetooth-devices/xiaogui-ble
